setup.cfg
setup.py
pixivhack/__init__.py
pixivhack/__main__.py
pixivhack/cls_crawl.py
pixivhack/pixivhack.py
pixivhack.egg-info/PKG-INFO
pixivhack.egg-info/SOURCES.txt
pixivhack.egg-info/dependency_links.txt
pixivhack.egg-info/entry_points.txt
pixivhack.egg-info/requires.txt
pixivhack.egg-info/top_level.txt