Metadata-Version: 1.1
Name: pixivhack
Version: 0.1.5
Summary: Pixiv Hack is a tool to automatically crawl illustrations filtered by ratings on www.pixiv.net
Home-page: https://github.com/Chion82/PixivHack
Author: Chion82
Author-email: sdspeedonion@gmail.com
License: MIT
Keywords: pixiv,pixivhack,crawler,crawl
Platform: UNKNOWN
Classifier: Development Status :: 3 - Alpha
Classifier: Programming Language :: Python :: 2
Classifier: Programming Language :: Python :: 2.6
Classifier: Programming Language :: Python :: 2.7
